Workbook
Name Bankrupt_number: Statistics!$A$2:$A$33
Name Bankrupt_percentage: Bankrupt_number/100
Name Solvability: SolvencyRatio!$B$1:$CW$32
Name Solvability_percentage: Solvability/100

Sheet Charts
B5: Policy Score: | E5: =Statistics!B33 -> 0
B25: This shows the average of the 100 scenario scores. Your policy score is the average score in the final year. | I25: This shows the score per scenario. If the association goes bankrupt, the score drops to zero.
B49: The solvency per scenario. The asssociation is bankrupt as soon as the solvency drops below 20% (regardless of future developments) | I49: The percentage of scenarios where the association has gone bankrupt by that year. Bankrupt associations score 0 points.
B71: The average rent of all owned houses, per scenario. A higher rent improves the financial situation of the association. | I71: The average maintenance costs of all owned houses, per scenario. More costs worsen the financial situation of the association.
B95: The number of houses owned by the association, per scenario. Dropping below 180 is allowed but will hurt your score.
B118: The number of houses that have a low rent (less than 400+inflation). This must be at least 50 to score. | I118: The number of houses which have a certain sustainability level. Higher percentages result in a higher score.

Sheet SolvencyRatio
A1: 2019
A2: 2020
A3: 2021
A4: 2022
A5: 2023
A6: 2024
A7: 2025
A8: 2026
A9: 2027
A10: 2028
A11: 2029
A12: 2030
... A32: 2050
A35: In percentages: | CX35: Average | CY35: Bankrupt threshold
A36: =A1 -> 2019 | B36: =B1/100 -> 0 | C36: =C1/100 -> 0 | D36: =D1/100 -> 0 | E36: =E1/100 -> 0 | F36: =F1/100 -> 0 | G36: =G1/100 -> 0 | H36: =H1/100 -> 0 | I36: =I1/100 -> 0 | ... CX36: =CX1/100 -> 0 | CY36: =0.2 -> 0.2
A37: =A2 -> 2020 | B37: =B2/100 -> 0 | C37: =C2/100 -> 0 | D37: =D2/100 -> 0 | E37: =E2/100 -> 0 | F37: =F2/100 -> 0 | G37: =G2/100 -> 0 | H37: =H2/100 -> 0 | I37: =I2/100 -> 0 | ... CX37: =CX2/100 -> 0 | CY37: =0.2 -> 0.2
A38: =A3 -> 2021 | B38: =B3/100 -> 0 | C38: =C3/100 -> 0 | D38: =D3/100 -> 0 | E38: =E3/100 -> 0 | F38: =F3/100 -> 0 | G38: =G3/100 -> 0 | H38: =H3/100 -> 0 | I38: =I3/100 -> 0 | ... CX38: =CX3/100 -> 0 | CY38: =0.2 -> 0.2
A39: =A4 -> 2022 | B39: =B4/100 -> 0 | C39: =C4/100 -> 0 | D39: =D4/100 -> 0 | E39: =E4/100 -> 0 | F39: =F4/100 -> 0 | G39: =G4/100 -> 0 | H39: =H4/100 -> 0 | I39: =I4/100 -> 0 | ... CX39: =CX4/100 -> 0 | CY39: =0.2 -> 0.2
A40: =A5 -> 2023 | B40: =B5/100 -> 0 | C40: =C5/100 -> 0 | D40: =D5/100 -> 0 | E40: =E5/100 -> 0 | F40: =F5/100 -> 0 | G40: =G5/100 -> 0 | H40: =H5/100 -> 0 | I40: =I5/100 -> 0 | ... CX40: =CX5/100 -> 0 | CY40: =0.2 -> 0.2
A41: =A6 -> 2024 | B41: =B6/100 -> 0 | C41: =C6/100 -> 0 | D41: =D6/100 -> 0 | E41: =E6/100 -> 0 | F41: =F6/100 -> 0 | G41: =G6/100 -> 0 | H41: =H6/100 -> 0 | I41: =I6/100 -> 0 | ... CX41: =CX6/100 -> 0 | CY41: =0.2 -> 0.2
A42: =A7 -> 2025 | B42: =B7/100 -> 0 | C42: =C7/100 -> 0 | D42: =D7/100 -> 0 | E42: =E7/100 -> 0 | F42: =F7/100 -> 0 | G42: =G7/100 -> 0 | H42: =H7/100 -> 0 | I42: =I7/100 -> 0 | ... CX42: =CX7/100 -> 0 | CY42: =0.2 -> 0.2
A43: =A8 -> 2026 | B43: =B8/100 -> 0 | C43: =C8/100 -> 0 | D43: =D8/100 -> 0 | E43: =E8/100 -> 0 | F43: =F8/100 -> 0 | G43: =G8/100 -> 0 | H43: =H8/100 -> 0 | I43: =I8/100 -> 0 | ... CX43: =CX8/100 -> 0 | CY43: =0.2 -> 0.2
A44: =A9 -> 2027 | B44: =B9/100 -> 0 | C44: =C9/100 -> 0 | D44: =D9/100 -> 0 | E44: =E9/100 -> 0 | F44: =F9/100 -> 0 | G44: =G9/100 -> 0 | H44: =H9/100 -> 0 | I44: =I9/100 -> 0 | ... CX44: =CX9/100 -> 0 | CY44: =0.2 -> 0.2
A45: =A10 -> 2028 | B45: =B10/100 -> 0 | C45: =C10/100 -> 0 | D45: =D10/100 -> 0 | E45: =E10/100 -> 0 | F45: =F10/100 -> 0 | G45: =G10/100 -> 0 | H45: =H10/100 -> 0 | I45: =I10/100 -> 0 | ... CX45: =CX10/100 -> 0 | CY45: =0.2 -> 0.2
A46: =A11 -> 2029 | B46: =B11/100 -> 0 | C46: =C11/100 -> 0 | D46: =D11/100 -> 0 | E46: =E11/100 -> 0 | F46: =F11/100 -> 0 | G46: =G11/100 -> 0 | H46: =H11/100 -> 0 | I46: =I11/100 -> 0 | ... CX46: =CX11/100 -> 0 | CY46: =0.2 -> 0.2
A47: =A12 -> 2030 | B47: =B12/100 -> 0 | C47: =C12/100 -> 0 | D47: =D12/100 -> 0 | E47: =E12/100 -> 0 | F47: =F12/100 -> 0 | G47: =G12/100 -> 0 | H47: =H12/100 -> 0 | I47: =I12/100 -> 0 | ... CX47: =CX12/100 -> 0 | CY47: =0.2 -> 0.2
... A67: =A32 -> 2050 | B67: =B32/100 -> 0 | C67: =C32/100 -> 0 | D67: =D32/100 -> 0 | E67: =E32/100 -> 0 | F67: =F32/100 -> 0 | G67: =G32/100 -> 0 | H67: =H32/100 -> 0 | I67: =I32/100 -> 0 | ... CX67: =CX32/100 -> 0 | CY67: =0.2 -> 0.2

Sheet Number of houses
A1: 2019 | CX1: 180
A2: 2020 | CX2: 180
A3: 2021 | CX3: 180
A4: 2022 | CX4: 180
A5: 2023 | CX5: 180
A6: 2024 | CX6: 180
A7: 2025 | CX7: 180
A8: 2026 | CX8: 180
A9: 2027 | CX9: 180
A10: 2028 | CX10: 180
A11: 2029 | CX11: 180
A12: 2030 | CX12: 180
... A32: 2050 | CX32: 180

Sheet Average rent
A1: 2019
A2: 2020
A3: 2021
A4: 2022
A5: 2023
A6: 2024
A7: 2025
A8: 2026
A9: 2027
A10: 2028
A11: 2029
A12: 2030
... A32: 2050

Sheet Average sustainability
A1: 2019
A2: 2020
A3: 2021
A4: 2022
A5: 2023
A6: 2024
A7: 2025
A8: 2026
A9: 2027
A10: 2028
A11: 2029
A12: 2030
... A32: 2050

Sheet Average maintenance
A1: 2019
A2: 2020
A3: 2021
A4: 2022
A5: 2023
A6: 2024
A7: 2025
A8: 2026
A9: 2027
A10: 2028
A11: 2029
A12: 2030
... A32: 2050

Sheet Debt
A1: 2019
A2: 2020
A3: 2021
A4: 2022
A5: 2023
A6: 2024
A7: 2025
A8: 2026
A9: 2027
A10: 2028
A11: 2029
A12: 2030
... A32: 2050

Sheet Interest
A1: 2019
A2: 2020
A3: 2021
A4: 2022
A5: 2023
A6: 2024
A7: 2025
A8: 2026
A9: 2027
A10: 2028
A11: 2029
A12: 2030
... A32: 2050

Sheet Scores
A1: 2019
A2: 2020
A3: 2021
A4: 2022
A5: 2023
A6: 2024
A7: 2025
A8: 2026
A9: 2027
A10: 2028
A11: 2029
A12: 2030
... A32: 2050

Sheet Statistics
A1: Number of bankrupt | B1: Score | C1: Quality | D1: Rent | E1: Interest | F1: Number of houses | H1: Score number of houses | I1: Score Rent | J1: Score Quality

Sheet Number of cheap houses
A1: 2019 | CX1: 50
A2: 2020 | CX2: 50
A3: 2021 | CX3: 50
A4: 2022 | CX4: 50
A5: 2023 | CX5: 50
A6: 2024 | CX6: 50
A7: 2025 | CX7: 50
A8: 2026 | CX8: 50
A9: 2027 | CX9: 50
A10: 2028 | CX10: 50
A11: 2029 | CX11: 50
A12: 2030 | CX12: 50
... A32: 2050 | CX32: 50

Sheet Number of bad houses
A1: 2019
A2: 2020
A3: 2021
A4: 2022
A5: 2023
A6: 2024
A7: 2025
A8: 2026
A9: 2027
A10: 2028
A11: 2029
A12: 2030
... A32: 2050
A35: Percentage of houses with sufficient quality
A36: =A1 -> 2019 | B36: =1-B1/'Number of houses'!B1 -> #DIV/0! | C36: =1-C1/'Number of houses'!C1 -> #DIV/0! | D36: =1-D1/'Number of houses'!D1 -> #DIV/0! | E36: =1-E1/'Number of houses'!E1 -> #DIV/0! | F36: =1-F1/'Number of houses'!F1 -> #DIV/0! | G36: =1-G1/'Number of houses'!G1 -> #DIV/0! | H36: =1-H1/'Number of houses'!H1 -> #DIV/0! | I36: =1-I1/'Number of houses'!I1 -> #DIV/0! | ... CW36: =1-CW1/'Number of houses'!CW1 -> #DIV/0!
A37: =A2 -> 2020 | B37: =1-B2/'Number of houses'!B2 -> #DIV/0! | C37: =1-C2/'Number of houses'!C2 -> #DIV/0! | D37: =1-D2/'Number of houses'!D2 -> #DIV/0! | E37: =1-E2/'Number of houses'!E2 -> #DIV/0! | F37: =1-F2/'Number of houses'!F2 -> #DIV/0! | G37: =1-G2/'Number of houses'!G2 -> #DIV/0! | H37: =1-H2/'Number of houses'!H2 -> #DIV/0! | I37: =1-I2/'Number of houses'!I2 -> #DIV/0! | ... CW37: =1-CW2/'Number of houses'!CW2 -> #DIV/0!
A38: =A3 -> 2021 | B38: =1-B3/'Number of houses'!B3 -> #DIV/0! | C38: =1-C3/'Number of houses'!C3 -> #DIV/0! | D38: =1-D3/'Number of houses'!D3 -> #DIV/0! | E38: =1-E3/'Number of houses'!E3 -> #DIV/0! | F38: =1-F3/'Number of houses'!F3 -> #DIV/0! | G38: =1-G3/'Number of houses'!G3 -> #DIV/0! | H38: =1-H3/'Number of houses'!H3 -> #DIV/0! | I38: =1-I3/'Number of houses'!I3 -> #DIV/0! | ... CW38: =1-CW3/'Number of houses'!CW3 -> #DIV/0!
A39: =A4 -> 2022 | B39: =1-B4/'Number of houses'!B4 -> #DIV/0! | C39: =1-C4/'Number of houses'!C4 -> #DIV/0! | D39: =1-D4/'Number of houses'!D4 -> #DIV/0! | E39: =1-E4/'Number of houses'!E4 -> #DIV/0! | F39: =1-F4/'Number of houses'!F4 -> #DIV/0! | G39: =1-G4/'Number of houses'!G4 -> #DIV/0! | H39: =1-H4/'Number of houses'!H4 -> #DIV/0! | I39: =1-I4/'Number of houses'!I4 -> #DIV/0! | ... CW39: =1-CW4/'Number of houses'!CW4 -> #DIV/0!
A40: =A5 -> 2023 | B40: =1-B5/'Number of houses'!B5 -> #DIV/0! | C40: =1-C5/'Number of houses'!C5 -> #DIV/0! | D40: =1-D5/'Number of houses'!D5 -> #DIV/0! | E40: =1-E5/'Number of houses'!E5 -> #DIV/0! | F40: =1-F5/'Number of houses'!F5 -> #DIV/0! | G40: =1-G5/'Number of houses'!G5 -> #DIV/0! | H40: =1-H5/'Number of houses'!H5 -> #DIV/0! | I40: =1-I5/'Number of houses'!I5 -> #DIV/0! | ... CW40: =1-CW5/'Number of houses'!CW5 -> #DIV/0!
A41: =A6 -> 2024 | B41: =1-B6/'Number of houses'!B6 -> #DIV/0! | C41: =1-C6/'Number of houses'!C6 -> #DIV/0! | D41: =1-D6/'Number of houses'!D6 -> #DIV/0! | E41: =1-E6/'Number of houses'!E6 -> #DIV/0! | F41: =1-F6/'Number of houses'!F6 -> #DIV/0! | G41: =1-G6/'Number of houses'!G6 -> #DIV/0! | H41: =1-H6/'Number of houses'!H6 -> #DIV/0! | I41: =1-I6/'Number of houses'!I6 -> #DIV/0! | ... CW41: =1-CW6/'Number of houses'!CW6 -> #DIV/0!
A42: =A7 -> 2025 | B42: =1-B7/'Number of houses'!B7 -> #DIV/0! | C42: =1-C7/'Number of houses'!C7 -> #DIV/0! | D42: =1-D7/'Number of houses'!D7 -> #DIV/0! | E42: =1-E7/'Number of houses'!E7 -> #DIV/0! | F42: =1-F7/'Number of houses'!F7 -> #DIV/0! | G42: =1-G7/'Number of houses'!G7 -> #DIV/0! | H42: =1-H7/'Number of houses'!H7 -> #DIV/0! | I42: =1-I7/'Number of houses'!I7 -> #DIV/0! | ... CW42: =1-CW7/'Number of houses'!CW7 -> #DIV/0!
A43: =A8 -> 2026 | B43: =1-B8/'Number of houses'!B8 -> #DIV/0! | C43: =1-C8/'Number of houses'!C8 -> #DIV/0! | D43: =1-D8/'Number of houses'!D8 -> #DIV/0! | E43: =1-E8/'Number of houses'!E8 -> #DIV/0! | F43: =1-F8/'Number of houses'!F8 -> #DIV/0! | G43: =1-G8/'Number of houses'!G8 -> #DIV/0! | H43: =1-H8/'Number of houses'!H8 -> #DIV/0! | I43: =1-I8/'Number of houses'!I8 -> #DIV/0! | ... CW43: =1-CW8/'Number of houses'!CW8 -> #DIV/0!
A44: =A9 -> 2027 | B44: =1-B9/'Number of houses'!B9 -> #DIV/0! | C44: =1-C9/'Number of houses'!C9 -> #DIV/0! | D44: =1-D9/'Number of houses'!D9 -> #DIV/0! | E44: =1-E9/'Number of houses'!E9 -> #DIV/0! | F44: =1-F9/'Number of houses'!F9 -> #DIV/0! | G44: =1-G9/'Number of houses'!G9 -> #DIV/0! | H44: =1-H9/'Number of houses'!H9 -> #DIV/0! | I44: =1-I9/'Number of houses'!I9 -> #DIV/0! | ... CW44: =1-CW9/'Number of houses'!CW9 -> #DIV/0!
A45: =A10 -> 2028 | B45: =1-B10/'Number of houses'!B10 -> #DIV/0! | C45: =1-C10/'Number of houses'!C10 -> #DIV/0! | D45: =1-D10/'Number of houses'!D10 -> #DIV/0! | E45: =1-E10/'Number of houses'!E10 -> #DIV/0! | F45: =1-F10/'Number of houses'!F10 -> #DIV/0! | G45: =1-G10/'Number of houses'!G10 -> #DIV/0! | H45: =1-H10/'Number of houses'!H10 -> #DIV/0! | I45: =1-I10/'Number of houses'!I10 -> #DIV/0! | ... CW45: =1-CW10/'Number of houses'!CW10 -> #DIV/0!
A46: =A11 -> 2029 | B46: =1-B11/'Number of houses'!B11 -> #DIV/0! | C46: =1-C11/'Number of houses'!C11 -> #DIV/0! | D46: =1-D11/'Number of houses'!D11 -> #DIV/0! | E46: =1-E11/'Number of houses'!E11 -> #DIV/0! | F46: =1-F11/'Number of houses'!F11 -> #DIV/0! | G46: =1-G11/'Number of houses'!G11 -> #DIV/0! | H46: =1-H11/'Number of houses'!H11 -> #DIV/0! | I46: =1-I11/'Number of houses'!I11 -> #DIV/0! | ... CW46: =1-CW11/'Number of houses'!CW11 -> #DIV/0!
A47: =A12 -> 2030 | B47: =1-B12/'Number of houses'!B12 -> #DIV/0! | C47: =1-C12/'Number of houses'!C12 -> #DIV/0! | D47: =1-D12/'Number of houses'!D12 -> #DIV/0! | E47: =1-E12/'Number of houses'!E12 -> #DIV/0! | F47: =1-F12/'Number of houses'!F12 -> #DIV/0! | G47: =1-G12/'Number of houses'!G12 -> #DIV/0! | H47: =1-H12/'Number of houses'!H12 -> #DIV/0! | I47: =1-I12/'Number of houses'!I12 -> #DIV/0! | ... CW47: =1-CW12/'Number of houses'!CW12 -> #DIV/0!
... A67: =A32 -> 2050 | B67: =1-B32/'Number of houses'!B32 -> #DIV/0! | C67: =1-C32/'Number of houses'!C32 -> #DIV/0! | D67: =1-D32/'Number of houses'!D32 -> #DIV/0! | E67: =1-E32/'Number of houses'!E32 -> #DIV/0! | F67: =1-F32/'Number of houses'!F32 -> #DIV/0! | G67: =1-G32/'Number of houses'!G32 -> #DIV/0! | H67: =1-H32/'Number of houses'!H32 -> #DIV/0! | I67: =1-I32/'Number of houses'!I32 -> #DIV/0! | ... CW67: =1-CW32/'Number of houses'!CW32 -> #DIV/0!
